README.md
pi-image-prep.py
setup.cfg
setup.py
image_prep/__ini__.py
image_prep/image_prep.py
pi_image_prep.egg-info/PKG-INFO
pi_image_prep.egg-info/SOURCES.txt
pi_image_prep.egg-info/dependency_links.txt
pi_image_prep.egg-info/top_level.txt