Metadata-Version: 2.1
Name: pi-image-prep
Version: 0.1.1
Summary: Prepare Raspbian for headless install
Home-page: https://gitlab.com/rveach/pi-image-prep
Author: Ryan Veach
Author-email: rveach@gmail.com
License: MIT
Keywords: Raspberry,Pi,Raspbian
Platform: UNKNOWN
Classifier: Development Status :: 4 - Beta
Classifier: Intended Audience :: Developers
Classifier: Intended Audience :: Information Technology
Classifier: Intended Audience :: System Administrators
Classifier: License :: OSI Approved :: MIT License
Classifier: Topic :: Software Development :: Libraries :: Python Modules
Classifier: Topic :: Internet
Classifier: Operating System :: POSIX :: Linux
Classifier: Programming Language :: Python :: 3
Classifier: Programming Language :: Python :: 3.5
Classifier: Programming Language :: Python :: 3.6
Classifier: Programming Language :: Python :: 3.7
Classifier: Programming Language :: Python :: 3.8
Requires-Python: >=3.5
